rkguiv2/__init__.py
rkguiv2/api.py
rkguiv2/app.py
rkguiv2/core.py
rkguiv2/dialogs.py
rkguiv2/dock.py
rkguiv2/events.py
rkguiv2/filedialogs.py
rkguiv2/layout.py
rkguiv2/menubar.py
rkguiv2/sidebar.py
rkguiv2/splitter.py
rkguiv2/statusbar.py
rkguiv2/tabs.py
rkguiv2/theme.py
rkguiv2/toolbar.py
rkguiv2/treeview.py
rkguiv2/webview.py
rkguiv2/widgets.py
rkguiv2-0.1.1.dist-info/METADATA
rkguiv2-0.1.1.dist-info/WHEEL
rkguiv2-0.1.1.dist-info/top_level.txt
rkguiv2-0.1.1.dist-info/RECORD
