Metadata-Version: 2.4
Name: rkguiv2
Version: 0.1.1
Summary: A Just GUI on Python
Author: 11iii
Author-email: 11iiimnjup@gmail.com
Classifier: Programming Language :: Python :: 3
Classifier: Operating System :: OS Independent
Classifier: License :: OSI Approved :: MIT License
Classifier: Topic :: Software Development :: Libraries :: Application Frameworks
Requires-Python: >=3.8
Requires-Dist: pywebview>=3.5
Dynamic: author
Dynamic: author-email
Dynamic: classifier
Dynamic: description
Dynamic: requires-dist
Dynamic: requires-python
Dynamic: summary
